datagrid/__init__.py
datagrid/_typing.py
datagrid/_version.py
datagrid/app.py
datagrid/colab_env.py
datagrid/datatypes.py
datagrid/st_utils.py
datagrid/utils.py
datagrid/_datatypes/__init__.py
datagrid/_datatypes/audio.py
datagrid/_datatypes/base.py
datagrid/_datatypes/colormaps.py
datagrid/_datatypes/curve.py
datagrid/_datatypes/datagrid.py
datagrid/_datatypes/embedding.py
datagrid/_datatypes/image.py
datagrid/_datatypes/mask.py
datagrid/_datatypes/math_3d.py
datagrid/_datatypes/pointcloud.py
datagrid/_datatypes/serialize.py
datagrid/_datatypes/tensor.py
datagrid/_datatypes/text.py
datagrid/_datatypes/utils.py
datagrid/_datatypes/video.py
datagrid/server/__init__.py
datagrid/server/computed_columns.py
datagrid/server/queries.py
datagrid/server/utils.py
datagrid-1.0.15.dist-info/LICENSE
datagrid-1.0.15.dist-info/METADATA
datagrid-1.0.15.dist-info/WHEEL
datagrid-1.0.15.dist-info/top_level.txt
datagrid-1.0.15.dist-info/RECORD
